setup.cfg
setup.py
eveasy/__init__.py
eveasy.egg-info/PKG-INFO
eveasy.egg-info/SOURCES.txt
eveasy.egg-info/dependency_links.txt
eveasy.egg-info/entry_points.txt
eveasy.egg-info/not-zip-safe
eveasy.egg-info/top_level.txt