Metadata-Version: 1.0
Name: eveasy
Version: 0.1dev
Summary: Easily View Environment Variables
Home-page: UNKNOWN
Author: Logan Henson
Author-email: logan@loganhenson.com
License: UNKNOWN
Keywords: Environment,Variables
Platform: UNKNOWN
